bbgo/__init__.py
bbgo/data/__init__.py
bbgo/data/balance.py
bbgo/data/depth.py
bbgo/data/error.py
bbgo/data/event.py
bbgo/data/kline.py
bbgo/data/order.py
bbgo/data/submit_order.py
bbgo/data/subscription.py
bbgo/data/ticker.py
bbgo/data/trade.py
bbgo/enums/__init__.py
bbgo/enums/channel_type.py
bbgo/enums/depth_type.py
bbgo/enums/event_type.py
bbgo/enums/order_type.py
bbgo/enums/side_type.py
bbgo/handlers/__init__.py
bbgo/handlers/balance.py
bbgo/handlers/book.py
bbgo/handlers/error.py
bbgo/handlers/handler.py
bbgo/handlers/kline.py
bbgo/handlers/order.py
bbgo/handlers/snapshot.py
bbgo/handlers/ticker.py
bbgo/handlers/trade.py
bbgo/handlers/update.py
bbgo/services.py
bbgo/stream.py
bbgo/utils/__init__.py
bbgo/utils/convert.py
bbgo/utils/grpc_utils.py
bbgo_pb2.py
bbgo_pb2_grpc.py
bbgo-0.1.10.dist-info/LICENSE
bbgo-0.1.10.dist-info/METADATA
bbgo-0.1.10.dist-info/WHEEL
bbgo-0.1.10.dist-info/RECORD
